{
  "isColoring": true,
  "grid": 30,
  "pallete": [
    "#FF0000",
    "##FFFF00",
    "#000000"
  ],
  "rects": [
    {
      "indexRect": 107,
      "indexColor": 2
    },
    {
      "indexRect": 108,
      "indexColor": 2
    },
    {
      "indexRect": 109,
      "indexColor": 2
    },
    {
      "indexRect": 136,
      "indexColor": 2
    },
    {
      "indexRect": 135,
      "indexColor": 2
    },
    {
      "indexRect": 137,
      "indexColor": 2
    },
    {
      "indexRect": 141,
      "indexColor": 2
    },
    {
      "indexRect": 142,
      "indexColor": 2
    },
    {
      "indexRect": 143,
      "indexColor": 2
    },
    {
      "indexRect": 165,
      "indexColor": 2
    },
    {
      "indexRect": 195,
      "indexColor": 2
    },
    {
      "indexRect": 226,
      "indexColor": 2
    },
    {
      "indexRect": 257,
      "indexColor": 2
    },
    {
      "indexRect": 287,
      "indexColor": 2
    },
    {
      "indexRect": 318,
      "indexColor": 2
    },
    {
      "indexRect": 349,
      "indexColor": 2
    },
    {
      "indexRect": 380,
      "indexColor": 2
    },
    {
      "indexRect": 412,
      "indexColor": 2
    },
    {
      "indexRect": 443,
      "indexColor": 2
    },
    {
      "indexRect": 475,
      "indexColor": 2
    },
    {
      "indexRect": 507,
      "indexColor": 2
    },
    {
      "indexRect": 508,
      "indexColor": 2
    },
    {
      "indexRect": 539,
      "indexColor": 2
    },
    {
      "indexRect": 175,
      "indexColor": 2
    },
    {
      "indexRect": 207,
      "indexColor": 2
    },
    {
      "indexRect": 238,
      "indexColor": 2
    },
    {
      "indexRect": 269,
      "indexColor": 2
    },
    {
      "indexRect": 301,
      "indexColor": 2
    },
    {
      "indexRect": 332,
      "indexColor": 2
    },
    {
      "indexRect": 363,
      "indexColor": 2
    },
    {
      "indexRect": 394,
      "indexColor": 2
    },
    {
      "indexRect": 424,
      "indexColor": 2
    },
    {
      "indexRect": 455,
      "indexColor": 2
    },
    {
      "indexRect": 485,
      "indexColor": 2
    },
    {
      "indexRect": 515,
      "indexColor": 2
    },
    {
      "indexRect": 514,
      "indexColor": 2
    },
    {
      "indexRect": 545,
      "indexColor": 2
    },
    {
      "indexRect": 478,
      "indexColor": 2
    },
    {
      "indexRect": 479,
      "indexColor": 2
    },
    {
      "indexRect": 480,
      "indexColor": 2
    },
    {
      "indexRect": 481,
      "indexColor": 2
    },
    {
      "indexRect": 482,
      "indexColor": 2
    },
    {
      "indexRect": 571,
      "indexColor": 2
    },
    {
      "indexRect": 572,
      "indexColor": 2
    },
    {
      "indexRect": 573,
      "indexColor": 2
    },
    {
      "indexRect": 574,
      "indexColor": 2
    },
    {
      "indexRect": 575,
      "indexColor": 2
    },
    {
      "indexRect": 606,
      "indexColor": 2
    },
    {
      "indexRect": 602,
      "indexColor": 2
    },
    {
      "indexRect": 634,
      "indexColor": 2
    },
    {
      "indexRect": 666,
      "indexColor": 2
    },
    {
      "indexRect": 636,
      "indexColor": 2
    },
    {
      "indexRect": 537,
      "indexColor": 2
    },
    {
      "indexRect": 567,
      "indexColor": 2
    },
    {
      "indexRect": 597,
      "indexColor": 2
    },
    {
      "indexRect": 627,
      "indexColor": 2
    },
    {
      "indexRect": 658,
      "indexColor": 2
    },
    {
      "indexRect": 690,
      "indexColor": 2
    },
    {
      "indexRect": 691,
      "indexColor": 2
    },
    {
      "indexRect": 661,
      "indexColor": 2
    },
    {
      "indexRect": 693,
      "indexColor": 2
    },
    {
      "indexRect": 662,
      "indexColor": 2
    },
    {
      "indexRect": 631,
      "indexColor": 2
    },
    {
      "indexRect": 600,
      "indexColor": 2
    },
    {
      "indexRect": 569,
      "indexColor": 2
    },
    {
      "indexRect": 723,
      "indexColor": 2
    },
    {
      "indexRect": 754,
      "indexColor": 2
    },
    {
      "indexRect": 785,
      "indexColor": 2
    },
    {
      "indexRect": 784,
      "indexColor": 2
    },
    {
      "indexRect": 815,
      "indexColor": 2
    },
    {
      "indexRect": 846,
      "indexColor": 2
    },
    {
      "indexRect": 847,
      "indexColor": 2
    },
    {
      "indexRect": 848,
      "indexColor": 2
    },
    {
      "indexRect": 849,
      "indexColor": 2
    },
    {
      "indexRect": 850,
      "indexColor": 2
    },
    {
      "indexRect": 788,
      "indexColor": 2
    },
    {
      "indexRect": 819,
      "indexColor": 2
    },
    {
      "indexRect": 758,
      "indexColor": 2
    },
    {
      "indexRect": 759,
      "indexColor": 2
    },
    {
      "indexRect": 760,
      "indexColor": 2
    },
    {
      "indexRect": 792,
      "indexColor": 2
    },
    {
      "indexRect": 823,
      "indexColor": 2
    },
    {
      "indexRect": 854,
      "indexColor": 2
    },
    {
      "indexRect": 855,
      "indexColor": 2
    },
    {
      "indexRect": 856,
      "indexColor": 2
    },
    {
      "indexRect": 857,
      "indexColor": 2
    },
    {
      "indexRect": 858,
      "indexColor": 2
    },
    {
      "indexRect": 827,
      "indexColor": 2
    },
    {
      "indexRect": 796,
      "indexColor": 2
    },
    {
      "indexRect": 795,
      "indexColor": 2
    },
    {
      "indexRect": 764,
      "indexColor": 2
    },
    {
      "indexRect": 733,
      "indexColor": 2
    },
    {
      "indexRect": 577,
      "indexColor": 2
    },
    {
      "indexRect": 608,
      "indexColor": 2
    },
    {
      "indexRect": 639,
      "indexColor": 2
    },
    {
      "indexRect": 670,
      "indexColor": 2
    },
    {
      "indexRect": 701,
      "indexColor": 2
    },
    {
      "indexRect": 671,
      "indexColor": 2
    },
    {
      "indexRect": 703,
      "indexColor": 2
    },
    {
      "indexRect": 704,
      "indexColor": 2
    },

    {
      "indexRect": 674,
      "indexColor": 2
    },
    {
      "indexRect": 643,
      "indexColor": 2
    },
    {
      "indexRect": 611,
      "indexColor": 2
    },
    {
      "indexRect": 579,
      "indexColor": 2
    },
    {
      "indexRect": 547,
      "indexColor": 2
    },
    {
      "indexRect": 289,
      "indexColor": 2
    },
    {
      "indexRect": 320,
      "indexColor": 2
    },
    {
      "indexRect": 299,
      "indexColor": 2
    },
    {
      "indexRect": 330,
      "indexColor": 2
    },
    {
      "indexRect": 321,
      "indexColor": 2
    },
    {
      "indexRect": 322,
      "indexColor": 2
    },
    {
      "indexRect": 323,
      "indexColor": 2
    },
    {
      "indexRect": 324,
      "indexColor": 2
    },
    {
      "indexRect": 325,
      "indexColor": 2
    },
    {
      "indexRect": 326,
      "indexColor": 2
    },
    {
      "indexRect": 327,
      "indexColor": 2
    },
    {
      "indexRect": 328,
      "indexColor": 2
    },
    {
      "indexRect": 329,
      "indexColor": 2
    },
    {
      "indexRect": 357,
      "indexColor": 2
    },
    {
      "indexRect": 356,
      "indexColor": 2
    },
    {
      "indexRect": 355,
      "indexColor": 2
    },
    {
      "indexRect": 138,
      "indexColor": 0
    },
    {
      "indexRect": 139,
      "indexColor": 0
    },
    {
      "indexRect": 140,
      "indexColor": 0
    },
    {
      "indexRect": 174,
      "indexColor": 0
    },
    {
      "indexRect": 173,
      "indexColor": 0
    },
    {
      "indexRect": 172,
      "indexColor": 0
    },
    {
      "indexRect": 171,
      "indexColor": 0
    },
    {
      "indexRect": 170,
      "indexColor": 0
    },
    {
      "indexRect": 169,
      "indexColor": 0
    },
    {
      "indexRect": 168,
      "indexColor": 0
    },
    {
      "indexRect": 167,
      "indexColor": 0
    },
    {
      "indexRect": 166,
      "indexColor": 0
    },
    {
      "indexRect": 196,
      "indexColor": 0
    },
    {
      "indexRect": 227,
      "indexColor": 0
    },
    {
      "indexRect": 258,
      "indexColor": 0
    },
    {
      "indexRect": 199,
      "indexColor": 0
    },
    {
      "indexRect": 230,
      "indexColor": 0
    },
    {
      "indexRect": 206,
      "indexColor": 0
    },
    {
      "indexRect": 268,
      "indexColor": 0
    },
    {
      "indexRect": 237,
      "indexColor": 0
    },
    {
      "indexRect": 203,
      "indexColor": 0
    },
    {
      "indexRect": 234,
      "indexColor": 0
    },
    {
      "indexRect": 264,
      "indexColor": 0
    },
    {
      "indexRect": 263,
      "indexColor": 0
    },
    {
      "indexRect": 262,
      "indexColor": 0
    },
    {
      "indexRect": 231,
      "indexColor": 0
    },
    {
      "indexRect": 200,
      "indexColor": 0
    },
    {
      "indexRect": 201,
      "indexColor": 0
    },
    {
      "indexRect": 233,
      "indexColor": 0
    },
    {
      "indexRect": 232,
      "indexColor": 0
    },
    {
      "indexRect": 202,
      "indexColor": 0
    },
    {
      "indexRect": 197,
      "indexColor": 1
    },
    {
      "indexRect": 228,
      "indexColor": 1
    },
    {
      "indexRect": 259,
      "indexColor": 1
    },
    {
      "indexRect": 290,
      "indexColor": 1
    },
    {
      "indexRect": 260,
      "indexColor": 1
    },
    {
      "indexRect": 291,
      "indexColor": 1
    },
    {
      "indexRect": 229,
      "indexColor": 1
    },
    {
      "indexRect": 198,
      "indexColor": 1
    },
    {
      "indexRect": 261,
      "indexColor": 1
    },
    {
      "indexRect": 292,
      "indexColor": 1
    },
    {
      "indexRect": 293,
      "indexColor": 1
    },
    {
      "indexRect": 294,
      "indexColor": 1
    },
    {
      "indexRect": 295,
      "indexColor": 1
    },
    {
      "indexRect": 296,
      "indexColor": 1
    },
    {
      "indexRect": 297,
      "indexColor": 1
    },
    {
      "indexRect": 298,
      "indexColor": 1
    },
    {
      "indexRect": 267,
      "indexColor": 1
    },
    {
      "indexRect": 236,
      "indexColor": 1
    },
    {
      "indexRect": 205,
      "indexColor": 1
    },
    {
      "indexRect": 204,
      "indexColor": 1
    },
    {
      "indexRect": 235,
      "indexColor": 1
    },
    {
      "indexRect": 266,
      "indexColor": 1
    },
    {
      "indexRect": 265,
      "indexColor": 1
    },
    {
      "indexRect": 288,
      "indexColor": 0
    },
    {
      "indexRect": 319,
      "indexColor": 0
    },
    {
      "indexRect": 350,
      "indexColor": 0
    },
    {
      "indexRect": 381,
      "indexColor": 0
    },
    {
      "indexRect": 300,
      "indexColor": 0
    },
    {
      "indexRect": 331,
      "indexColor": 0
    },
    {
      "indexRect": 362,
      "indexColor": 0
    },
    {
      "indexRect": 393,
      "indexColor": 0
    },
    {
      "indexRect": 413,
      "indexColor": 0
    },
    {
      "indexRect": 444,
      "indexColor": 0
    },
    {
      "indexRect": 423,
      "indexColor": 0
    },
    {
      "indexRect": 454,
      "indexColor": 0
    },
    {
      "indexRect": 351,
      "indexColor": 1
    },
    {
      "indexRect": 382,
      "indexColor": 1
    },
    {
      "indexRect": 383,
      "indexColor": 1
    },
    {
      "indexRect": 384,
      "indexColor": 1
    },
    {
      "indexRect": 385,
      "indexColor": 1
    },
    {
      "indexRect": 386,
      "indexColor": 1
    },
    {
      "indexRect": 387,
      "indexColor": 1
    },
    {
      "indexRect": 388,
      "indexColor": 1
    },
    {
      "indexRect": 389,
      "indexColor": 1
    },
    {
      "indexRect": 390,
      "indexColor": 1
    },
    {
      "indexRect": 391,
      "indexColor": 1
    },
    {
      "indexRect": 392,
      "indexColor": 1
    },
    {
      "indexRect": 361,
      "indexColor": 1
    },
    {
      "indexRect": 422,
      "indexColor": 1
    },
    {
      "indexRect": 453,
      "indexColor": 1
    },
    {
      "indexRect": 484,
      "indexColor": 0
    },
    {
      "indexRect": 483,
      "indexColor": 1
    },
    {
      "indexRect": 452,
      "indexColor": 1
    },
    {
      "indexRect": 421,
      "indexColor": 1
    },
    {
      "indexRect": 420,
      "indexColor": 1
    },
    {
      "indexRect": 451,
      "indexColor": 1
    },
    {
      "indexRect": 450,
      "indexColor": 1
    },
    {
      "indexRect": 419,
      "indexColor": 1
    },
    {
      "indexRect": 418,
      "indexColor": 1
    },
    {
      "indexRect": 448,
      "indexColor": 1
    },
    {
      "indexRect": 449,
      "indexColor": 1
    },
    {
      "indexRect": 417,
      "indexColor": 1
    },
    {
      "indexRect": 416,
      "indexColor": 1
    },
    {
      "indexRect": 447,
      "indexColor": 1
    },
    {
      "indexRect": 415,
      "indexColor": 1
    },
    {
      "indexRect": 446,
      "indexColor": 1
    },
    {
      "indexRect": 477,
      "indexColor": 1
    },
    {
      "indexRect": 476,
      "indexColor": 0
    },
    {
      "indexRect": 414,
      "indexColor": 1
    },
    {
      "indexRect": 445,
      "indexColor": 1
    },
    {
      "indexRect": 538,
      "indexColor": 0
    },
    {
      "indexRect": 568,
      "indexColor": 0
    },
    {
      "indexRect": 628,
      "indexColor": 0
    },
    {
      "indexRect": 629,
      "indexColor": 0
    },
    {
      "indexRect": 660,
      "indexColor": 0
    },
    {
      "indexRect": 659,
      "indexColor": 0
    },
    {
      "indexRect": 546,
      "indexColor": 0
    },
    {
      "indexRect": 578,
      "indexColor": 0
    },
    {
      "indexRect": 641,
      "indexColor": 0
    },
    {
      "indexRect": 672,
      "indexColor": 0
    },
    {
      "indexRect": 642,
      "indexColor": 0
    },
    {
      "indexRect": 673,
      "indexColor": 0
    },
    {
      "indexRect": 540,
      "indexColor": 0
    },
    {
      "indexRect": 541,
      "indexColor": 0
    },
    {
      "indexRect": 542,
      "indexColor": 0
    },
    {
      "indexRect": 544,
      "indexColor": 0
    },
    {
      "indexRect": 543,
      "indexColor": 0
    },
    {
      "indexRect": 509,
      "indexColor": 1
    },
    {
      "indexRect": 510,
      "indexColor": 1
    },
    {
      "indexRect": 511,
      "indexColor": 1
    },
    {
      "indexRect": 512,
      "indexColor": 1
    },
    {
      "indexRect": 513,
      "indexColor": 1
    },
    {
      "indexRect": 640,
      "indexColor": 1
    },
    {
      "indexRect": 610,
      "indexColor": 1
    },
    {
      "indexRect": 609,
      "indexColor": 1
    },
    {
      "indexRect": 598,
      "indexColor": 1
    },
    {
      "indexRect": 599,
      "indexColor": 1
    },
    {
      "indexRect": 630,
      "indexColor": 1
    },
    {
      "indexRect": 816,
      "indexColor": 0
    },
    {
      "indexRect": 817,
      "indexColor": 0
    },
    {
      "indexRect": 818,
      "indexColor": 0
    },
    {
      "indexRect": 787,
      "indexColor": 0
    },
    {
      "indexRect": 755,
      "indexColor": 0
    },
    {
      "indexRect": 786,
      "indexColor": 0
    },
    {
      "indexRect": 724,
      "indexColor": 1
    },
    {
      "indexRect": 725,
      "indexColor": 1
    },
    {
      "indexRect": 756,
      "indexColor": 1
    },
    {
      "indexRect": 757,
      "indexColor": 1
    },
    {
      "indexRect": 763,
      "indexColor": 0
    },
    {
      "indexRect": 793,
      "indexColor": 0
    },
    {
      "indexRect": 824,
      "indexColor": 0
    },
    {
      "indexRect": 794,
      "indexColor": 0
    },
    {
      "indexRect": 826,
      "indexColor": 0
    },
    {
      "indexRect": 825,
      "indexColor": 0
    },
    {
      "indexRect": 761,
      "indexColor": 1
    },
    {
      "indexRect": 762,
      "indexColor": 1
    },
    {
      "indexRect": 731,
      "indexColor": 1
    },
    {
      "indexRect": 732,
      "indexColor": 1
    },
    {
      "indexRect": 570,
      "indexColor": 0
    },
    {
      "indexRect": 601,
      "indexColor": 0
    },
    {
      "indexRect": 663,
      "indexColor": 0
    },
    {
      "indexRect": 694,
      "indexColor": 0
    },
    {
      "indexRect": 632,
      "indexColor": 0
    },
    {
      "indexRect": 633,
      "indexColor": 0
    },
    {
      "indexRect": 664,
      "indexColor": 0
    },
    {
      "indexRect": 695,
      "indexColor": 0
    },
    {
      "indexRect": 726,
      "indexColor": 0
    },
    {
      "indexRect": 665,
      "indexColor": 0
    },
    {
      "indexRect": 696,
      "indexColor": 0
    },
    {
      "indexRect": 727,
      "indexColor": 0
    },
    {
      "indexRect": 728,
      "indexColor": 0
    },
    {
      "indexRect": 697,
      "indexColor": 0
    },
    {
      "indexRect": 698,
      "indexColor": 0
    },
    {
      "indexRect": 729,
      "indexColor": 0
    },
    {
      "indexRect": 730,
      "indexColor": 0
    },
    {
      "indexRect": 699,
      "indexColor": 0
    },
    {
      "indexRect": 700,
      "indexColor": 0
    },
    {
      "indexRect": 669,
      "indexColor": 0
    },
    {
      "indexRect": 638,
      "indexColor": 0
    },
    {
      "indexRect": 607,
      "indexColor": 0
    },
    {
      "indexRect": 637,
      "indexColor": 0
    },
    {
      "indexRect": 668,
      "indexColor": 0
    },
    {
      "indexRect": 667,
      "indexColor": 0
    },
    {
      "indexRect": 576,
      "indexColor": 0
    }
  ]
}